ciqar/__init__.py
ciqar/application.py
ciqar/input/__init__.py
ciqar/input/sourcefiles.py
ciqar/input/violations.py
ciqar/input/linter/mypy_logfile.py
ciqar/input/linter/pyright_json.py
ciqar/input/linter/result_parser.py
ciqar/input/linter/ruff_json.py
ciqar/report/generator.py
ciqar/report/jinja_wrapper.py
ciqar/report/datagen/__init__.py
ciqar/report/datagen/_base.py
ciqar/report/datagen/listings.py
ciqar/report/datagen/rules.py
ciqar/report/datagen/sources.py
ciqar/report/datagen/summary.py
ciqar/report/datagen/violations.py
ciqar/templates/api.py
ciqar/templates/html_detailed/__init__.py
ciqar/templates/html_detailed/index.html.in
ciqar/templates/html_detailed/listing.html.in
ciqar/templates/html_detailed/rule_details.html.in
ciqar/templates/html_detailed/rule_list.html.in
ciqar/templates/html_detailed/sort-table.js
ciqar/templates/html_detailed/source_list.html.in
ciqar/templates/html_detailed/style.css
ciqar/templates/html_singlepage/__init__.py
ciqar/templates/html_singlepage/index.html.in
ciqar-1.1.0.dist-info/entry_points.txt
ciqar-1.1.0.dist-info/LICENSE
ciqar-1.1.0.dist-info/WHEEL
ciqar-1.1.0.dist-info/METADATA
ciqar-1.1.0.dist-info/RECORD
