Metadata-Version: 2.3
Name: ciqar
Version: 1.1.0
Summary: Ciqar is a tool for creating reports from different code quality analyzers output.
Keywords: linter,report,code analysis,code quality
Author: Thomas Wesenigk <thw-oss@fomori.de>
Requires-Python: >=3.12
Classifier: Development Status :: 3 - Alpha
Classifier: Environment :: Console
Classifier: Intended Audience :: Developers
Classifier: License :: OSI Approved :: GNU Affero General Public License v3 or later (AGPLv3+)
Classifier: Operating System :: POSIX :: Linux
Classifier: Programming Language :: Python :: 3.12
Classifier: Topic :: Software Development
Classifier: Topic :: Software Development :: Quality Assurance
Requires-Dist: Jinja2<4.0
Requires-Dist: typing_extensions<5.0
Requires-Dist: invoke ; extra == "devtools"
Requires-Dist: flit<4 ; extra == "devtools"
Requires-Dist: pip-tools ; extra == "devtools"
Requires-Dist: pylint ; extra == "devtools"
Requires-Dist: pytest ; extra == "devtools"
Requires-Dist: pytest-cov ; extra == "devtools"
Requires-Dist: pyfakefs ; extra == "devtools"
Requires-Dist: mypy ; extra == "devtools"
Requires-Dist: pyright ; extra == "devtools"
Requires-Dist: black ; extra == "devtools"
Requires-Dist: black-junit ; extra == "devtools"
Requires-Dist: ruff ; extra == "devtools"
Project-URL: Home, https://codeberg.org/Aardjon/ciqar/
Project-URL: Source, https://codeberg.org/Aardjon/ciqar.git
Provides-Extra: devtools
